ajv.programme-0.3.6.dist-info/DESCRIPTION.rst
ajv.programme-0.3.6.dist-info/METADATA
ajv.programme-0.3.6.dist-info/RECORD
ajv.programme-0.3.6.dist-info/WHEEL
ajv.programme-0.3.6.dist-info/entry_points.txt
ajv.programme-0.3.6.dist-info/metadata.json
ajv.programme-0.3.6.dist-info/top_level.txt
programme/__init__.py
programme/base.tsv
programme/cli.py
programme/style.css
programme/template.jinja
programme/version.txt
