Metadata-Version: 2.0
Name: ajv.programme
Version: 0.3.6
Summary: Simple programme generator
Home-page: https://github.com/andrew-vant/programme
Author: Andrew Vant
Author-email: ajv@andrewvant.com
License: UNKNOWN
Platform: UNKNOWN
Classifier: Development Status :: 3 - Alpha
Classifier: Natural Language :: English
Classifier: Operating System :: OS Independent
Classifier: Programming Language :: Python :: 3
Requires-Dist: jinja2
